{
  "employees": [
    {
      "id": 1,
      "name": "Jessica Younker"
    },
    {
      "id": 3,
      "name": "Zoe LeBlanc"
    },
    {
      "id": 4,
      "name": "Blaise Roberts"
    }
  ],
  "locations": [
    {
      "id": 1,
      "name": "Nashville North",
      "address": "500 Circle Way"
    },
    {
      "id": 2,
      "name": "Nashville South",
      "address": "10101 Binary Court"
    }
  ],
  "animals": [
    {
      "name": "lala",
      "breed": "doggo",
      "employeeId": 1,
      "ownerId": 2,
      "id": 10
    },
    {
      "id": 11,
      "name": "Matthew",
      "breed": "Good Dog",
      "employeeId": 3
    },
    {
      "name": "Drew",
      "breed": "Bad Dog",
      "employeeId": 4,
      "ownerId": 1,
      "id": 12
    },
    {
      "name": "Danny",
      "breed": "Horrid Dog",
      "employeeId": 3,
      "ownerId": 1,
      "id": 13
    }
  ],
  "owners": [
    {
      "id": 1,
      "name": "Ryan Tanay"
    },
    {
      "id": 2,
      "name": "Tyler Carpenter"
    },
    {
      "id": 3,
      "name": "Dani Adkins"
    },
    {
      "id": 4,
      "name": "Adam Oswalt"
    },
    {
      "id": 5,
      "name": "Fletcher Bangs"
    }
  ],
  "search": [
    {}
  ]
}